pubpy/__init__.py
pubpy/main.py
pubpy/savefig.py
pubpy/theme_publication.py
pubpy-1.0.2.dist-info/LICENSE
pubpy-1.0.2.dist-info/METADATA
pubpy-1.0.2.dist-info/WHEEL
pubpy-1.0.2.dist-info/top_level.txt
pubpy-1.0.2.dist-info/RECORD
