Metadata-Version: 2.1
Name: pubpy
Version: 1.0.2
Summary: Scientific theme of Matplotlib for publication 
Home-page: https://github.com/haihuilab/pubpy/
Author: Haihui Zhang
Author-email: hanfei19@gmail.com
Maintainer: Haihui Zhang
Maintainer-email: hanfei19@gmail.com
License: BSD 3-Clause License
Keywords: matplotlib-style-sheets,matplotlib-figures,scientific-papers,thesis-template,matplotlib-styles,python
Classifier: Framework :: Matplotlib
Classifier: License :: OSI Approved :: BSD License
Classifier: Programming Language :: Python :: 3
License-File: LICENSE
Requires-Dist: matplotlib
